LICENSE.txt
README.md
setup.py
cwtvla/__init__.py
cwtvla/aes_cipher.py
cwtvla/aes_tables.py
cwtvla/analysis.py
cwtvla/cw_convenience.py
cwtvla/funcs.py
cwtvla/key_schedule.py
cwtvla/ktp.py
cwtvla.egg-info/PKG-INFO
cwtvla.egg-info/SOURCES.txt
cwtvla.egg-info/dependency_links.txt
cwtvla.egg-info/requires.txt
cwtvla.egg-info/top_level.txt