Metadata-Version: 1.0
Name: cwtvla
Version: 0.1.3
Summary: ChipWhisperer Test Vector Leakage Assessment Library
Home-page: UNKNOWN
Author: Alex Dewar
Author-email: adewar@newae.com
License: GPLv2+
Platform: UNKNOWN
